{
  "documents": [
    {
      "text": "### Deep Research: Mathematics Failed to compile final report. Details: 'url'",
      "source": "deep_research_report.md",
      "counts": {
        "deep": 1,
        "research": 1,
        "mathematics": 1,
        "failed": 1,
        "compile": 1,
        "final": 1,
        "report": 1,
        "details": 1,
        "url": 1
      },
      "length": 9
    },
    {
      "text": "# Unit 1: Calculus in Mathematics ## Chapter 1: Limits and Continuity ### 1.1 Definitions of Key Terms **Limits:** A limit is a mathematical concept that describes the behavior of a function as its input approaches a certain value, or as it gets arbitrarily close to that value. **Continuity:** A function is continuous at a point if it can be drawn without lifting your pencil from the paper and passes through every point in its domain. Continuity implies that the limit exists for all points in its domain. ### 1.2 Formal Definitions of Key Terms - **Limit:** The value to which a function approaches as its input gets arbitrarily close to a certain value.",
      "source": "unit_1_study_guide.md",
      "counts": {
        "unit": 1,
        "calculus": 1,
        "mathematics": 1,
        "chapter": 1,
        "limits": 2,
        "continuity": 3,
        "definitions": 2,
        "key": 2,
        "terms": 2,
        "limit": 3,
        "mathematical": 1,
        "concept": 1,
        "describes": 1,
        "behavior": 1,
        "function": 3,
        "its": 4,
        "input": 2,
        "approaches": 2,
        "certain": 2,
        "value": 4,
        "gets": 2,
        "arbitrarily": 2,
        "close": 2,
        "continuous": 1,
        "point": 2,
        "can": 1,
        "drawn": 1,
        "without": 1,
        "lifting": 1,
        "pencil": 1,
        "paper": 1,
        "passes": 1,
        "through": 1,
        "every": 1,
        "domain": 2,
        "implies": 1,
        "exists": 1,
        "all": 1,
        "points": 1,
        "formal": 1,
        "which": 1
      },
      "length": 65
    },
    {
      "text": "- **Limit:** The value to which a function approaches as its input gets arbitrarily close to a certain value. - **Continuity:** A function is continuous at a point if it can be drawn without lifting your pencil from the paper and passes through every point in its domain. ### 1.3 Code Examples, Formulas, or Practical Exercises #### Example: Finding the Limit of a Function ```python import math def f(x): return x ** 2 - 4 limit = math.limit(f, x=2) print(limit) # Output: 2.0 ``` #### Example: Continuity Check ```python def continuous_function(x): return math.cos(x) is_continuous = all(continuous_function(x) for x in [-1, 0, 1]) print(is_continuous) # Output: True ``` ### Chapter 2: Differentia",
      "source": "unit_1_study_guide.md",
      "counts": {
        "limit": 5,
        "value": 2,
        "which": 1,
        "function": 3,
        "approaches": 1,
        "its": 2,
        "input": 1,
        "gets": 1,
        "arbitrarily": 1,
        "close": 1,
        "certain": 1,
        "continuity": 2,
        "continuous": 1,
        "point": 2,
        "can": 1,
        "drawn": 1,
        "without": 1,
        "lifting": 1,
        "pencil": 1,
        "paper": 1,
        "passes": 1,
        "through": 1,
        "every": 1,
        "domain": 1,
        "code": 1,
        "examples": 1,
        "formulas": 1,
        "practical": 1,
        "exercises": 1,
        "example": 2,
        "finding": 1,
        "python": 2,
        "import": 1,
        "math": 3,
        "def": 2,
        "return": 2,
        "print": 2,
        "output": 2,
        "check": 1,
        "cos": 1,
        "all": 1,
        "true": 1,
        "chapter": 1,
        "differentia": 1
      },
      "length": 62
    },
    {
      "text": "return math.cos(x) is_continuous = all(continuous_function(x) for x in [-1, 0, 1]) print(is_continuous) # Output: True ``` ### Chapter 2: Differentiation Rules #### 2.1 Definitions of Key Terms - **Derivative:** The derivative of a function is the rate at which the function's value changes with respect to its input. - **Chain Rule:** If \\( f(g(x)) \\) is a composite function, then the derivative of \\( f(g(x)) \\) is given by: \\[ (f \\circ g)'(x) = f'(g(x)) \\cdot g'(x) \\] where \\( f' \\) and \\( g' \\) are the derivatives of \\( f \\) and \\( g \\), respectively.",
      "source": "unit_1_study_guide.md",
      "counts": {
        "return": 1,
        "math": 1,
        "cos": 1,
        "all": 1,
        "print": 1,
        "output": 1,
        "true": 1,
        "chapter": 1,
        "differentiation": 1,
        "rules": 1,
        "definitions": 1,
        "key": 1,
        "terms": 1,
        "derivative": 3,
        "function": 3,
        "rate": 1,
        "which": 1,
        "value": 1,
        "changes": 1,
        "respect": 1,
        "its": 1,
        "input": 1,
        "chain": 1,
        "rule": 1,
        "composite": 1,
        "then": 1,
        "given": 1,
        "circ": 1,
        "cdot": 1,
        "where": 1,
        "derivatives": 1,
        "respectively": 1
      },
      "length": 36
    },
    {
      "text": "ectively. #### 2.2 Formal Definitions of Key Terms - **Derivative:** The derivative of a function is the value of the tangent line to its graph at a point. - **Chain Rule:** If \\( f(g(x)) \\) is a composite function, then the derivative of \\( f(g(x)) \\) is given by: \\[ (f \\circ g)'(x) = f'(g(x)) \\cdot g'(x) \\] where \\( f' \\) and \\( g' \\) are the derivatives of \\( f \\) and \\( g \\), respectively. ### Chapter 3: Integration #### 3.1 Definitions of Key Terms - **Integration:** The integral of a function is the antiderivative of that function. - **Antiderivatives:** A function whose derivative is another function is called an antiderivative of that function.",
      "source": "unit_1_study_guide.md",
      "counts": {
        "ectively": 1,
        "formal": 1,
        "definitions": 2,
        "key": 2,
        "terms": 2,
        "derivative": 4,
        "function": 7,
        "value": 1,
        "tangent": 1,
        "line": 1,
        "its": 1,
        "graph": 1,
        "point": 1,
        "chain": 1,
        "rule": 1,
        "composite": 1,
        "then": 1,
        "given": 1,
        "circ": 1,
        "cdot": 1,
        "where": 1,
        "derivatives": 1,
        "respectively": 1,
        "chapter": 1,
        "integration": 2,
        "integral": 1,
        "antiderivative": 2,
        "antiderivatives": 1,
        "whose": 1,
        "another": 1,
        "called": 1
      },
      "length": 45
    },
    {
      "text": "tiderivatives:** A function whose derivative is another function is called an antiderivative of that function. - **Indefinite Integrals:** An indefinite integral is an antiderivative of a function. It represents all possible antiderivatives of the function. #### 3.2 Formal Definitions of Key Terms - **Integration:** The integral of a function \\( f(x) \\) with respect to \\( x \\) is given by: \\[ \\int f(x) \\, dx = F(x) + C \\] where \\( F(x) \\) is an antiderivative of \\( f(x) \\), and \\( C \\) is a constant. - **Antiderivatives:** A function whose derivative is another function is called an antiderivative of that function. It represents all possible antiderivatives of the function.",
      "source": "unit_1_study_guide.md",
      "counts": {
        "tiderivatives": 1,
        "function": 10,
        "whose": 2,
        "derivative": 2,
        "another": 2,
        "called": 2,
        "antiderivative": 4,
        "indefinite": 2,
        "integrals": 1,
        "integral": 2,
        "represents": 2,
        "all": 2,
        "possible": 2,
        "antiderivatives": 3,
        "formal": 1,
        "definitions": 1,
        "key": 1,
        "terms": 1,
        "integration": 1,
        "respect": 1,
        "given": 1,
        "int": 1,
        "where": 1,
        "constant": 1
      },
      "length": 47
    },
    {
      "text": "vative is another function is called an antiderivative of that function. It represents all possible antiderivatives of the function. \\[ F'(x) = g(x) \\] where \\( G(x) \\) is an antiderivative of \\( g(x) \\). ### Chapter 4: Applications and Examples #### Example: Finding the Area Under a Curve ```python import sympy as sp def area_under_curve(x_values): y_values = [x ** 2 for x in x_values] return sp.integrate(y_values, (x, -1, 1)) area = area_under_curve([0, 1, 4]) print(area) # Output: 3.16666666666667 ``` #### Example: Finding the Volume of a Sphere ```python from sympy import symbols def volume_of_sphere(radius): return (4/3) * sp.pi * radius ** 3 volume = volume_of_sphere(2) print(volume) #",
      "source": "unit_1_study_guide.md",
      "counts": {
        "vative": 1,
        "another": 1,
        "function": 3,
        "called": 1,
        "antiderivative": 2,
        "represents": 1,
        "all": 1,
        "possible": 1,
        "antiderivatives": 1,
        "where": 1,
        "chapter": 1,
        "applications": 1,
        "examples": 1,
        "example": 2,
        "finding": 2,
        "area": 3,
        "under": 1,
        "curve": 1,
        "python": 2,
        "import": 2,
        "sympy": 2,
        "def": 2,
        "return": 2,
        "integrate": 1,
        "print": 2,
        "output": 1,
        "16666666666667": 1,
        "volume": 3,
        "sphere": 1,
        "symbols": 1,
        "radius": 2
      },
      "length": 47
    },
    {
      "text": "here ```python from sympy import symbols def volume_of_sphere(radius): return (4/3) * sp.pi * radius ** 3 volume = volume_of_sphere(2) print(volume) # Output: 10.8169578969248 ``` #### Example: Finding the Area of a Circle ```python from sympy import pi, symbols def area_of_circle(radius): return pi * radius **",
      "source": "unit_1_study_guide.md",
      "counts": {
        "here": 1,
        "python": 2,
        "sympy": 2,
        "import": 2,
        "symbols": 2,
        "def": 2,
        "radius": 4,
        "return": 2,
        "volume": 2,
        "print": 1,
        "output": 1,
        "8169578969248": 1,
        "example": 1,
        "finding": 1,
        "area": 1,
        "circle": 1
      },
      "length": 26
    },
    {
      "text": "# Unit 2: Linear Algebra in Mathematics ## Chapter 1: Vector Spaces ### Definition of a Vector Space A vector space is a mathematical structure that consists of a set of elements (called vectors) and a binary operation (called addition), which combines two vectors to produce another vector. The set of all vectors forms a vector space under this operation. #### Subtopics: - **Vector Spaces**: A collection of vectors where the operations are defined. - **Subspaces**: Subsets of a vector space that satisfy certain conditions. - **Spanning Sets**: Vectors in the vector space that can be used to form any vector in the space.",
      "source": "unit_2_study_guide.md",
      "counts": {
        "unit": 1,
        "linear": 1,
        "algebra": 1,
        "mathematics": 1,
        "chapter": 1,
        "vector": 9,
        "spaces": 2,
        "definition": 1,
        "space": 6,
        "mathematical": 1,
        "structure": 1,
        "consists": 1,
        "set": 2,
        "elements": 1,
        "called": 2,
        "vectors": 5,
        "binary": 1,
        "operation": 2,
        "addition": 1,
        "which": 1,
        "combines": 1,
        "two": 1,
        "produce": 1,
        "another": 1,
        "all": 1,
        "forms": 1,
        "under": 1,
        "subtopics": 1,
        "collection": 1,
        "where": 1,
        "operations": 1,
        "defined": 1,
        "subspaces": 1,
        "subsets": 1,
        "satisfy": 1,
        "certain": 1,
        "conditions": 1,
        "spanning": 1,
        "sets": 1,
        "can": 1,
        "used": 1,
        "form": 1,
        "any": 1
      },
      "length": 64
    },
    {
      "text": "Vectors in the vector space that can be used to form any vector in the space. - **Linear Independence**: A set of vectors is linearly independent if they cannot be expressed as a linear combination of other vectors. ### Example: Real Numbers The real numbers \\(\\mathbb{R}\\) are a vector space over the field \\(\\mathbb{Q}\\), where \\(\\mathbb{Q}\\) represents the rational numbers. The operations in this vector space include addition, subtraction, and multiplication by scalars (real numbers).",
      "source": "unit_2_study_guide.md",
      "counts": {
        "vectors": 3,
        "vector": 4,
        "space": 4,
        "can": 1,
        "used": 1,
        "form": 1,
        "any": 1,
        "linear": 2,
        "independence": 1,
        "set": 1,
        "linearly": 1,
        "independent": 1,
        "they": 1,
        "cannot": 1,
        "expressed": 1,
        "combination": 1,
        "other": 1,
        "example": 1,
        "real": 3,
        "numbers": 4,
        "mathbb": 3,
        "over": 1,
        "field": 1,
        "where": 1,
        "represents": 1,
        "rational": 1,
        "operations": 1,
        "include": 1,
        "addition": 1,
        "subtraction": 1,
        "multiplication": 1,
        "scalars": 1
      },
      "length": 48
    },
    {
      "text": "al numbers R = np.arange(10) # Additive identity identity = R + 0 # Scalar multiplication scalar = 2 result = scalar * R print(\"Real Numbers:\", R) print(\"Additive Identity:\", identity) print(\"Scalar Multiplication:\", result) ``` ### Formulas and Notations - **Vector Space**: \\( V \\) (vector space over \\(\\mathbb{R}\\)) - **Subspace**: \\( S \\subseteq V \\) such that every vector in \\( S \\) can be expressed as a linear combination of vectors in \\( S \\). - **Spanning Set**: A set of vectors that are linearly independent and span the entire vector space.",
      "source": "unit_2_study_guide.md",
      "counts": {
        "numbers": 2,
        "arange": 1,
        "additive": 2,
        "identity": 4,
        "scalar": 4,
        "multiplication": 2,
        "result": 2,
        "print": 3,
        "real": 1,
        "formulas": 1,
        "notations": 1,
        "vector": 4,
        "space": 3,
        "over": 1,
        "mathbb": 1,
        "subspace": 1,
        "subseteq": 1,
        "such": 1,
        "every": 1,
        "can": 1,
        "expressed": 1,
        "linear": 1,
        "combination": 1,
        "vectors": 2,
        "spanning": 1,
        "set": 2,
        "linearly": 1,
        "independent": 1,
        "span": 1,
        "entire": 1
      },
      "length": 49
    },
    {
      "text": "ce. ### Example: Vector Space over \\(\\mathbb{Q}\\) Consider the vector space \\(\\mathbb{R}^2\\) (the plane) with addition defined as: \\[ (x_1, x_2) + (y_1, y_2) = (x_1 + y_1, x_2 + y_2). \\] #### Code Example: ```python import numpy as np # Define vectors in R^2 v1 = np.array([1, 2]) v2 = np.array([3, 4]) # Addition result = v1 + v2 print(\"Vector Addition:\", result) ``` ### Linear Independence A set of vectors is linearly independent if the only solution to the equation \\( c_1 \\mathbf{u} + c_2 \\mathbf{v} = \\mathbf{0} \\) is \\( c_1 = 0, c_2 = 0 \\). #### Example: Consider the set of vectors \\(\\{(1, 0), (0, 1)\\}\\).",
      "source": "unit_2_study_guide.md",
      "counts": {
        "example": 3,
        "vector": 3,
        "space": 2,
        "over": 1,
        "mathbb": 2,
        "consider": 2,
        "plane": 1,
        "addition": 3,
        "defined": 1,
        "code": 1,
        "python": 1,
        "import": 1,
        "numpy": 1,
        "define": 1,
        "vectors": 3,
        "array": 2,
        "result": 2,
        "print": 1,
        "linear": 1,
        "independence": 1,
        "set": 2,
        "linearly": 1,
        "independent": 1,
        "only": 1,
        "solution": 1,
        "equation": 1,
        "mathbf": 3
      },
      "length": 43
    },
    {
      "text": "### Example: Consider the set of vectors \\(\\{(1, 0), (0, 1)\\}\\). These vectors are linearly independent because there is no non-trivial solution to the equation: \\[ c_1 (1, 0) + c_2 (0, 1) = (0, 0). \\] #### Code Example: ```python import numpy as np # Define vectors in R^2 v1 = np.array([1, 0]) v2 = np.array([0, 1]) # Check linear independence is_linearly_independent = v1[0] * v2[0] + v1[1] * v2[1] == 0 print(\"Vectors are Linearly Independent:\", is_linearly_independent) ``` ### Matrix Representation and Invertibility A matrix \\( A \\) in a vector space can be represented as an infinite-dimensional array of scalars.",
      "source": "unit_2_study_guide.md",
      "counts": {
        "example": 2,
        "consider": 1,
        "set": 1,
        "vectors": 4,
        "these": 1,
        "linearly": 2,
        "independent": 2,
        "because": 1,
        "there": 1,
        "non": 1,
        "trivial": 1,
        "solution": 1,
        "equation": 1,
        "code": 1,
        "python": 1,
        "import": 1,
        "numpy": 1,
        "define": 1,
        "array": 3,
        "check": 1,
        "linear": 1,
        "independence": 1,
        "print": 1,
        "matrix": 2,
        "representation": 1,
        "invertibility": 1,
        "vector": 1,
        "space": 1,
        "can": 1,
        "represented": 1,
        "infinite": 1,
        "dimensional": 1,
        "scalars": 1
      },
      "length": 42
    },
    {
      "text": "r space can be represented as an infinite-dimensional array of scalars. The determinant of \\( A \\), denoted \\( \\det(A) \\), gives the volume scaling factor when multiplying \\( A \\) by a unit vector. #### Example: Consider the 2x2 matrix: \\[ A = \\begin{pmatrix} 1 & 0 \\\\ 0 & 1 \\end{pmatrix}. \\] The determinant of this matrix is: \\[ \\det(A) = (1)(1) - (0)(0) = 1.",
      "source": "unit_2_study_guide.md",
      "counts": {
        "space": 1,
        "can": 1,
        "represented": 1,
        "infinite": 1,
        "dimensional": 1,
        "array": 1,
        "scalars": 1,
        "determinant": 2,
        "denoted": 1,
        "det": 2,
        "gives": 1,
        "volume": 1,
        "scaling": 1,
        "factor": 1,
        "when": 1,
        "multiplying": 1,
        "unit": 1,
        "vector": 1,
        "example": 1,
        "consider": 1,
        "2x2": 1,
        "matrix": 2,
        "begin": 1,
        "pmatrix": 2,
        "end": 1
      },
      "length": 29
    },
    {
      "text": ", determinant) ``` ### Inverse Matrix The inverse of a matrix \\( A \\) is defined as: \\[ A^{-1} = \\frac{1}{\\det(A)} \\text{adj}(A), \\] where \\(\\text{adj}(A)\\) is the adjugate matrix, which is the transpose of the cofactor matrix. #### Example: Consider",
      "source": "unit_2_study_guide.md",
      "counts": {
        "determinant": 1,
        "inverse": 2,
        "matrix": 4,
        "defined": 1,
        "frac": 1,
        "det": 1,
        "text": 2,
        "adj": 2,
        "where": 1,
        "adjugate": 1,
        "which": 1,
        "transpose": 1,
        "cofactor": 1,
        "example": 1,
        "consider": 1
      },
      "length": 21
    },
    {
      "text": "# Unit 3: Probability and Statistics in Mathematics ## Chapter 1: Basic Concepts ### 1.1 Probability **Definition:** A probability is a measure of how likely an event will occur. - **Example:** Rolling a fair six-sided die, where each side has an equal chance of landing face up. ### 1.2 Conditional Probability **Definition:** The probability of one event occurring given that another event has already occurred. - **Example:** If you flip a coin and it lands on heads, the probability of getting heads is 0.5 (or 50%). ### 1.3 Bayes' Theorem **Definition:** A theorem in probability theory that allows us to update our beliefs based on new evidence.",
      "source": "unit_3_study_guide.md",
      "counts": {
        "unit": 1,
        "probability": 7,
        "statistics": 1,
        "mathematics": 1,
        "chapter": 1,
        "basic": 1,
        "concepts": 1,
        "definition": 3,
        "measure": 1,
        "how": 1,
        "likely": 1,
        "event": 3,
        "will": 1,
        "occur": 1,
        "example": 2,
        "rolling": 1,
        "fair": 1,
        "six": 1,
        "sided": 1,
        "die": 1,
        "where": 1,
        "each": 1,
        "side": 1,
        "has": 2,
        "equal": 1,
        "chance": 1,
        "landing": 1,
        "face": 1,
        "conditional": 1,
        "one": 1,
        "occurring": 1,
        "given": 1,
        "another": 1,
        "already": 1,
        "occurred": 1,
        "flip": 1,
        "coin": 1,
        "lands": 1,
        "heads": 2,
        "getting": 1,
        "bayes": 1,
        "theorem": 2,
        "theory": 1,
        "allows": 1,
        "update": 1,
        "our": 1,
        "beliefs": 1,
        "based": 1,
        "new": 1,
        "evidence": 1
      },
      "length": 64
    },
    {
      "text": "nition:** A theorem in probability theory that allows us to update our beliefs based on new evidence. - **Formula:** P(A|B) = [P(B|A) * P(A)] / P(B) - **Example:** If we know that the weather is sunny, what's the probability it will rain tomorrow? We can use Bayes' Theorem to find this out: P(Rain|Sunny) = [P(Sunny|Rain) * P(Rain | Sunny)] / P(Sunny) ## Chapter 2: Random Variables ### 2.1 Random Variables **Definition:** A random variable is a measurable function from the sample space of an experiment to the real numbers. - **Example:** Rolling a fair six-sided die, where each roll can be represented by a number between 1 and 6.",
      "source": "unit_3_study_guide.md",
      "counts": {
        "nition": 1,
        "theorem": 2,
        "probability": 2,
        "theory": 1,
        "allows": 1,
        "update": 1,
        "our": 1,
        "beliefs": 1,
        "based": 1,
        "new": 1,
        "evidence": 1,
        "formula": 1,
        "example": 2,
        "know": 1,
        "weather": 1,
        "sunny": 5,
        "what": 1,
        "will": 1,
        "rain": 4,
        "tomorrow": 1,
        "can": 2,
        "use": 1,
        "bayes": 1,
        "find": 1,
        "out": 1,
        "chapter": 1,
        "random": 3,
        "variables": 2,
        "definition": 1,
        "variable": 1,
        "measurable": 1,
        "function": 1,
        "sample": 1,
        "space": 1,
        "experiment": 1,
        "real": 1,
        "numbers": 1,
        "rolling": 1,
        "fair": 1,
        "six": 1,
        "sided": 1,
        "die": 1,
        "where": 1,
        "each": 1,
        "roll": 1,
        "represented": 1,
        "number": 1,
        "between": 1
      },
      "length": 62
    },
    {
      "text": "a fair six-sided die, where each roll can be represented by a number between 1 and 6. ### 2.2 Cumulative Distribution Functions (CDF) **Definition:** The CDF of a random variable is the probability that the random variable takes on values less than or equal to a given value. - **Example:** If we have a random variable X, its CDF is defined as F(x) = P(X ≤ x). ### 2.3 Probability Distributions **Definition:** A distribution of a random variable is a collection of all possible outcomes and their corresponding probabilities. - **Examples:** The normal distribution, which has a bell-shaped curve with mean μ and standard deviation σ.",
      "source": "unit_3_study_guide.md",
      "counts": {
        "fair": 1,
        "six": 1,
        "sided": 1,
        "die": 1,
        "where": 1,
        "each": 1,
        "roll": 1,
        "can": 1,
        "represented": 1,
        "number": 1,
        "between": 1,
        "cumulative": 1,
        "distribution": 3,
        "functions": 1,
        "cdf": 3,
        "definition": 2,
        "random": 4,
        "variable": 4,
        "probability": 2,
        "takes": 1,
        "values": 1,
        "less": 1,
        "than": 1,
        "equal": 1,
        "given": 1,
        "value": 1,
        "example": 1,
        "have": 1,
        "its": 1,
        "defined": 1,
        "distributions": 1,
        "collection": 1,
        "all": 1,
        "possible": 1,
        "outcomes": 1,
        "their": 1,
        "corresponding": 1,
        "probabilities": 1,
        "examples": 1,
        "normal": 1,
        "which": 1,
        "has": 1,
        "bell": 1,
        "shaped": 1,
        "curve": 1,
        "mean": 1,
        "standard": 1,
        "deviation": 1
      },
      "length": 60
    },
    {
      "text": "ormal distribution, which has a bell-shaped curve with mean μ and standard deviation σ. ## Chapter 3: Probability Distributions ### 3.1 Discrete Distributions **Definition:** A discrete probability distribution is one where the random variable can take on only certain values. - **Examples:** Binomial distribution, Poisson distribution, geometric distribution. ### 3.2 Continuous Distributions **Definition:** A continuous probability distribution is one where the random variable can take any value within a given range. - **Examples:** Normal distribution, uniform distribution, exponential distribution.",
      "source": "unit_3_study_guide.md",
      "counts": {
        "ormal": 1,
        "distribution": 9,
        "which": 1,
        "has": 1,
        "bell": 1,
        "shaped": 1,
        "curve": 1,
        "mean": 1,
        "standard": 1,
        "deviation": 1,
        "chapter": 1,
        "probability": 3,
        "distributions": 3,
        "discrete": 2,
        "definition": 2,
        "one": 2,
        "where": 2,
        "random": 2,
        "variable": 2,
        "can": 2,
        "take": 2,
        "only": 1,
        "certain": 1,
        "values": 1,
        "examples": 2,
        "binomial": 1,
        "poisson": 1,
        "geometric": 1,
        "continuous": 2,
        "any": 1,
        "value": 1,
        "within": 1,
        "given": 1,
        "range": 1,
        "normal": 1,
        "uniform": 1,
        "exponential": 1
      },
      "length": 59
    },
    {
      "text": "ribution, uniform distribution, exponential distribution. ### 3.3 Moments of Distributions **Definition:** The mean (expected value) and variance are moments of a distribution. - **Example:** For a normal distribution with mean μ and standard deviation σ, the mean is μ and the variance is σ². ## Chapter 4: Expected Value **Definition:** The expected value of a random variable is the long-run average value of repetitions of the experiment it represents. - **Formula:** E(X) = ∑(x * P(x)) - **Example:** If you roll a fair six-sided die, the expected value is (1 + 2 + 3 + 4 + 5 + 6) / 6 = 3.5.",
      "source": "unit_3_study_guide.md",
      "counts": {
        "ribution": 1,
        "uniform": 1,
        "distribution": 4,
        "exponential": 1,
        "moments": 2,
        "distributions": 1,
        "definition": 2,
        "mean": 3,
        "expected": 4,
        "value": 5,
        "variance": 2,
        "example": 2,
        "normal": 1,
        "standard": 1,
        "deviation": 1,
        "chapter": 1,
        "random": 1,
        "variable": 1,
        "long": 1,
        "run": 1,
        "average": 1,
        "repetitions": 1,
        "experiment": 1,
        "represents": 1,
        "formula": 1,
        "roll": 1,
        "fair": 1,
        "six": 1,
        "sided": 1,
        "die": 1
      },
      "length": 46
    },
    {
      "text": "ed value is (1 + 2 + 3 + 4 + 5 + 6) / 6 = 3.5. ## Chapter 5: Variance and Standard Deviation **Definition:** The variance of a random variable is a measure of how spread out the values are. - **Formula:** Var(X) = E[(X - E(X))^2] - **Example:** If you roll a fair six-sided die, the variance is (1 + 4 + 9 + 6)^2 / 36 ≈ 0.75. ## Chapter 6: Central Limit Theorem **Definition:** A theorem in probability theory that states that the sum of a large number of independent and identically distributed random variables will be approximately normally distributed.",
      "source": "unit_3_study_guide.md",
      "counts": {
        "value": 1,
        "chapter": 2,
        "variance": 3,
        "standard": 1,
        "deviation": 1,
        "definition": 2,
        "random": 2,
        "variable": 1,
        "measure": 1,
        "how": 1,
        "spread": 1,
        "out": 1,
        "values": 1,
        "formula": 1,
        "var": 1,
        "example": 1,
        "roll": 1,
        "fair": 1,
        "six": 1,
        "sided": 1,
        "die": 1,
        "central": 1,
        "limit": 1,
        "theorem": 2,
        "probability": 1,
        "theory": 1,
        "states": 1,
        "sum": 1,
        "large": 1,
        "number": 1,
        "independent": 1,
        "identically": 1,
        "distributed": 2,
        "variables": 1,
        "will": 1,
        "approximately": 1,
        "normally": 1
      },
      "length": 44
    },
    {
      "text": "buted. - **Example:** If you roll a fair six-sided die many times, the distribution of the sample mean will approximate a normal distribution with mean 3.5 and standard deviation 1. ## Chapter 7: Normal Distribution **Definition:** A normal distribution is a continuous probability distribution that is symmetric about its mean. - **Example:** The heights of adult males in the United States are normally distributed with a mean of 68 inches and a standard deviation of 2.5 inches.",
      "source": "unit_3_study_guide.md",
      "counts": {
        "buted": 1,
        "example": 2,
        "roll": 1,
        "fair": 1,
        "six": 1,
        "sided": 1,
        "die": 1,
        "many": 1,
        "times": 1,
        "distribution": 5,
        "sample": 1,
        "mean": 4,
        "will": 1,
        "approximate": 1,
        "normal": 3,
        "standard": 2,
        "deviation": 2,
        "chapter": 1,
        "definition": 1,
        "continuous": 1,
        "probability": 1,
        "symmetric": 1,
        "about": 1,
        "its": 1,
        "heights": 1,
        "adult": 1,
        "males": 1,
        "united": 1,
        "states": 1,
        "normally": 1,
        "distributed": 1,
        "inches": 2
      },
      "length": 45
    },
    {
      "text": "on 1: **Answer:** A fair six-sided die has an expected value of 3.5, meaning that on average, you can expect to roll a number between 1 and 6 with equal probability. ### Question 2: **Answer:** The variance of the normal distribution is 0.75, which means that each data point in the distribution will be exactly 0.75 units away from the mean. ### Question 3: **Answer:** A fair six",
      "source": "unit_3_study_guide.md",
      "counts": {
        "answer": 3,
        "fair": 2,
        "six": 2,
        "sided": 1,
        "die": 1,
        "has": 1,
        "expected": 1,
        "value": 1,
        "meaning": 1,
        "average": 1,
        "can": 1,
        "expect": 1,
        "roll": 1,
        "number": 1,
        "between": 1,
        "equal": 1,
        "probability": 1,
        "question": 2,
        "variance": 1,
        "normal": 1,
        "distribution": 2,
        "which": 1,
        "means": 1,
        "each": 1,
        "data": 1,
        "point": 1,
        "will": 1,
        "exactly": 1,
        "units": 1,
        "away": 1,
        "mean": 1
      },
      "length": 37
    },
    {
      "text": "Certainly! Here's a comprehensive guide for \"Unit 4: Advanced Calculus\" in Mathematics, focusing on Chapters 1 through 3: --- # Advanced Calculus: Unit 4: Advanced Calculus ## Chapter 1: Integration Techniques ### Subtopics: - **Integration Techniques**: This section covers various techniques to integrate functions. It includes substitution rules, improper integrals, and antiderivatives. #### Definition of an Antiderivative: An antiderivative is a function whose derivative is the original function. **Example:** \\[ \\int x^2 \\, dx = \\frac{x^3}{3} + C \\] where \\( C \\) is the constant of integration.",
      "source": "unit_4_study_guide.md",
      "counts": {
        "certainly": 1,
        "here": 1,
        "comprehensive": 1,
        "guide": 1,
        "unit": 2,
        "advanced": 3,
        "calculus": 3,
        "mathematics": 1,
        "focusing": 1,
        "chapters": 1,
        "through": 1,
        "chapter": 1,
        "integration": 3,
        "techniques": 3,
        "subtopics": 1,
        "section": 1,
        "covers": 1,
        "various": 1,
        "integrate": 1,
        "functions": 1,
        "includes": 1,
        "substitution": 1,
        "rules": 1,
        "improper": 1,
        "integrals": 1,
        "antiderivatives": 1,
        "definition": 1,
        "antiderivative": 2,
        "function": 2,
        "whose": 1,
        "derivative": 1,
        "original": 1,
        "example": 1,
        "int": 1,
        "frac": 1,
        "where": 1,
        "constant": 1
      },
      "length": 48
    },
    {
      "text": "+ C \\] where \\( C \\) is the constant of integration. ### Formulas and Notations: - **Integration by Substitution**: If \\( u = g(x) \\), then \\( \\int g(x) \\, dx = \\int g(x) \\, dx \\). This formula simplifies the process of finding an antiderivative. #### Example: \\[ \\int x^2 \\, dx = \\frac{x^3}{3} + C \\] ### Examples: 1. **Example 1**: Find \\( \\int x \\, dx \\). - Use substitution: Let \\( u = x \\), then \\( du = dx \\). The integral becomes \\( \\int u \\, du = \\frac{u^2}{2} + C = \\frac{x^2}{2} + C \\). 2. **Example 2**: Find \\( \\int e^x \\, dx \\). - Use substitution: Let \\( u = e^x \\), then \\( du = e^x \\, dx \\). The integral becomes \\( \\int e^x \\, dx = e^x + C = e^{e^x} + C \\).",
      "source": "unit_4_study_guide.md",
      "counts": {
        "where": 1,
        "constant": 1,
        "integration": 2,
        "formulas": 1,
        "notations": 1,
        "substitution": 3,
        "then": 3,
        "int": 7,
        "formula": 1,
        "simplifies": 1,
        "process": 1,
        "finding": 1,
        "antiderivative": 1,
        "example": 3,
        "frac": 3,
        "examples": 1,
        "find": 2,
        "use": 2,
        "let": 2,
        "integral": 2,
        "becomes": 2
      },
      "length": 41
    },
    {
      "text": "ubstitution: Let \\( u = e^x \\), then \\( du = e^x \\, dx \\). The integral becomes \\( \\int e^x \\, dx = e^x + C = e^{e^x} + C \\). ### Practice Problems: 1. **Example 3**: Find \\( \\int x^2 \\, dx \\). - Use substitution: Let \\( u = x^2 \\), then \\( du = 2x \\, dx \\). The integral becomes \\( \\frac{u}{2} + C = \\frac{x^2}{2} + C \\). 2. **Example 4**: Find \\( \\int (e^x)^3 \\, dx \\). - Use substitution: Let \\( u = e^x \\), then \\( du = e^x \\, dx \\). The integral becomes \\( \\int u^3 \\, du = \\frac{u^4}{4} + C = \\frac{(e^x)^4}{4} + C = \\frac{e^{4x}}{4} + C \\). ### Recommended Exam Review Questions: 1. **Example 5**: Find \\( \\int x \\sin(x) \\, dx \\).",
      "source": "unit_4_study_guide.md",
      "counts": {
        "ubstitution": 1,
        "let": 3,
        "then": 3,
        "integral": 3,
        "becomes": 3,
        "int": 5,
        "practice": 1,
        "problems": 1,
        "example": 3,
        "find": 3,
        "use": 2,
        "substitution": 2,
        "frac": 5,
        "recommended": 1,
        "exam": 1,
        "review": 1,
        "questions": 1,
        "sin": 1
      },
      "length": 40
    },
    {
      "text": "# Recommended Exam Review Questions: 1. **Example 5**: Find \\( \\int x \\sin(x) \\, dx \\). - Use substitution: Let \\( u = \\sin(x) \\), then \\( du = \\cos(x) \\, dx \\). The integral becomes \\( \\int x \\sin(x) \\, dx = \\frac{x^2}{2} + C \\). 2. **Example 6**: Find \\( \\int e^{-x} \\, dx \\). - Use substitution: Let \\( u = e^{-x} \\), then \\( du = -e^{-x} \\, dx \\). The integral becomes \\( \\frac{1}{-u} + C = -\\frac{1}{e^x} + C \\). --- ## Chapter 2: Differential Equations ### Subtopics: - **Differential Equations**: This section covers various types of differential equations and their solutions.",
      "source": "unit_4_study_guide.md",
      "counts": {
        "recommended": 1,
        "exam": 1,
        "review": 1,
        "questions": 1,
        "example": 2,
        "find": 2,
        "int": 3,
        "sin": 3,
        "use": 2,
        "substitution": 2,
        "let": 2,
        "then": 2,
        "cos": 1,
        "integral": 2,
        "becomes": 2,
        "frac": 3,
        "chapter": 1,
        "differential": 3,
        "equations": 3,
        "subtopics": 1,
        "section": 1,
        "covers": 1,
        "various": 1,
        "types": 1,
        "their": 1,
        "solutions": 1
      },
      "length": 44
    },
    {
      "text": "ial equations and their solutions. #### Definition of a Differential Equation: A differential equation is an equation that relates one or more functions with its derivatives. **Example:** \\[ y'' + 3y' = e^x \\] ### Formulas and Notations: - **First Derivative**: \\( y' = \\frac{dy}{dx} \\) #### Example: \\[ y'' + 3y' = e^x \\] \\[ y'' = \\frac{d}{dx}(e^x) + 3\\left(\\frac{d}{dx}(e^x)\\right) = e^x + 3e^x = 4e^x \\] ### Examples: 1. **Example 7**: Find \\( y' \\) for the differential equation \\( y'' - 2y' + 5y = 0 \\). - Use the first derivative formula: \\( y' = \\frac{dy}{dx} \\). 2.",
      "source": "unit_4_study_guide.md",
      "counts": {
        "ial": 1,
        "equations": 1,
        "their": 1,
        "solutions": 1,
        "definition": 1,
        "differential": 3,
        "equation": 4,
        "relates": 1,
        "one": 1,
        "more": 1,
        "functions": 1,
        "its": 1,
        "derivatives": 1,
        "example": 3,
        "formulas": 1,
        "notations": 1,
        "first": 2,
        "derivative": 2,
        "frac": 4,
        "left": 1,
        "right": 1,
        "examples": 1,
        "find": 1,
        "use": 1,
        "formula": 1
      },
      "length": 37
    },
    {
      "text": "= \\frac{dy}{dx} \\). 2. **Example 8**: Solve the initial value problem: \\[ y''(x) + 4y'(x) + 3y(x) = e^x, \\quad y(0) = 1, \\quad y'(0) = -1 \\] - Use the first derivative formula and initial conditions to find \\( y(x) \\). ### Practice Problems",
      "source": "unit_4_study_guide.md",
      "counts": {
        "frac": 1,
        "example": 1,
        "solve": 1,
        "initial": 2,
        "value": 1,
        "problem": 1,
        "quad": 2,
        "use": 1,
        "first": 1,
        "derivative": 1,
        "formula": 1,
        "conditions": 1,
        "find": 1,
        "practice": 1,
        "problems": 1
      },
      "length": 17
    }
  ],
  "vocab": [
    "they",
    "new",
    "spread",
    "infinite",
    "distributed",
    "other",
    "define",
    "subspace",
    "include",
    "simplifies",
    "covers",
    "vectors",
    "coin",
    "collection",
    "geometric",
    "math",
    "frac",
    "various",
    "out",
    "practice",
    "within",
    "functions",
    "area",
    "expressed",
    "check",
    "sum",
    "values",
    "two",
    "questions",
    "which",
    "units",
    "how",
    "mathematics",
    "result",
    "subtopics",
    "mathematical",
    "rational",
    "improper",
    "function",
    "key",
    "differentiation",
    "such",
    "subseteq",
    "spaces",
    "buted",
    "det",
    "identically",
    "guide",
    "bell",
    "its",
    "vector",
    "beliefs",
    "respectively",
    "definitions",
    "advanced",
    "used",
    "transpose",
    "approximate",
    "points",
    "can",
    "space",
    "constant",
    "variables",
    "sided",
    "getting",
    "identity",
    "uniform",
    "formulas",
    "flip",
    "line",
    "denoted",
    "inverse",
    "variance",
    "invertibility",
    "cdot",
    "rule",
    "average",
    "recommended",
    "array",
    "includes",
    "scalars",
    "review",
    "conditional",
    "bayes",
    "details",
    "relates",
    "circ",
    "poisson",
    "dimensional",
    "passes",
    "occurred",
    "techniques",
    "describes",
    "rate",
    "applications",
    "allows",
    "multiplication",
    "based",
    "def",
    "concept",
    "integration",
    "experiment",
    "six",
    "non",
    "behavior",
    "theory",
    "long",
    "meaning",
    "what",
    "concepts",
    "tangent",
    "volume",
    "rules",
    "where",
    "cos",
    "variable",
    "here",
    "there",
    "ectively",
    "real",
    "sunny",
    "every",
    "circle",
    "cannot",
    "changes",
    "take",
    "combines",
    "set",
    "face",
    "discrete",
    "data",
    "over",
    "gets",
    "research",
    "binomial",
    "8169578969248",
    "takes",
    "trivial",
    "cofactor",
    "consider",
    "antiderivative",
    "operation",
    "return",
    "implies",
    "subspaces",
    "linearly",
    "conditions",
    "factor",
    "form",
    "multiplying",
    "use",
    "pencil",
    "consists",
    "shaped",
    "final",
    "expect",
    "rolling",
    "their",
    "approximately",
    "var",
    "combination",
    "will",
    "number",
    "has",
    "through",
    "mathbf",
    "matrix",
    "sample",
    "heights",
    "substitution",
    "under",
    "occur",
    "without",
    "states",
    "run",
    "sin",
    "pmatrix",
    "rain",
    "outcomes",
    "arange",
    "scalar",
    "theorem",
    "tiderivatives",
    "import",
    "differentia",
    "satisfy",
    "fair",
    "solve",
    "means",
    "inches",
    "finding",
    "calculus",
    "when",
    "approaches",
    "numpy",
    "die",
    "composite",
    "find",
    "definition",
    "answer",
    "central",
    "any",
    "point",
    "our",
    "binary",
    "males",
    "united",
    "chance",
    "types",
    "landing",
    "end",
    "each",
    "linear",
    "continuous",
    "ubstitution",
    "indefinite",
    "because",
    "domain",
    "these",
    "becomes",
    "unit",
    "url",
    "about",
    "another",
    "practical",
    "certain",
    "represents",
    "weather",
    "large",
    "normally",
    "only",
    "representation",
    "additive",
    "structure",
    "output",
    "chain",
    "scaling",
    "roll",
    "standard",
    "initial",
    "numbers",
    "comprehensive",
    "operations",
    "drawn",
    "gives",
    "focusing",
    "all",
    "then",
    "measurable",
    "more",
    "between",
    "plane",
    "moments",
    "exponential",
    "right",
    "2x2",
    "whose",
    "report",
    "nition",
    "chapter",
    "defined",
    "int",
    "have",
    "close",
    "deep",
    "given",
    "heads",
    "ribution",
    "mathbb",
    "solution",
    "update",
    "forms",
    "graph",
    "notations",
    "16666666666667",
    "problems",
    "produce",
    "equal",
    "ial",
    "times",
    "sympy",
    "terms",
    "respect",
    "limits",
    "many",
    "sets",
    "integrate",
    "exam",
    "examples",
    "measure",
    "true",
    "away",
    "cdf",
    "side",
    "differential",
    "than",
    "independence",
    "value",
    "exists",
    "arbitrarily",
    "code",
    "left",
    "begin",
    "exactly",
    "deviation",
    "determinant",
    "span",
    "range",
    "symmetric",
    "subtraction",
    "lifting",
    "exercises",
    "independent",
    "curve",
    "section",
    "antiderivatives",
    "equations",
    "radius",
    "corresponding",
    "event",
    "cumulative",
    "spanning",
    "derivatives",
    "know",
    "first",
    "vative",
    "failed",
    "expected",
    "integral",
    "field",
    "probability",
    "derivative",
    "limit",
    "distributions",
    "entire",
    "random",
    "original",
    "probabilities",
    "repetitions",
    "evidence",
    "chapters",
    "python",
    "lands",
    "algebra",
    "addition",
    "certainly",
    "sphere",
    "integrals",
    "symbols",
    "less",
    "paper",
    "solutions",
    "adj",
    "statistics",
    "called",
    "problem",
    "text",
    "equation",
    "quad",
    "continuity",
    "ormal",
    "normal",
    "one",
    "formula",
    "likely",
    "distribution",
    "occurring",
    "basic",
    "adjugate",
    "input",
    "already",
    "question",
    "formal",
    "let",
    "compile",
    "mean",
    "print",
    "elements",
    "possible",
    "represented",
    "process",
    "tomorrow",
    "example",
    "subsets",
    "adult"
  ],
  "df": {
    "url": 1,
    "deep": 1,
    "failed": 1,
    "mathematics": 5,
    "details": 1,
    "final": 1,
    "report": 1,
    "compile": 1,
    "research": 1,
    "its": 7,
    "close": 2,
    "drawn": 2,
    "concept": 1,
    "all": 7,
    "pencil": 2,
    "every": 3,
    "domain": 2,
    "lifting": 2,
    "unit": 5,
    "definitions": 4,
    "behavior": 1,
    "terms": 4,
    "input": 3,
    "gets": 2,
    "certain": 4,
    "limits": 1,
    "through": 3,
    "points": 1,
    "which": 8,
    "can": 11,
    "paper": 2,
    "formal": 3,
    "mathematical": 2,
    "without": 2,
    "calculus": 2,
    "approaches": 2,
    "function": 8,
    "limit": 3,
    "key": 4,
    "passes": 2,
    "chapter": 14,
    "describes": 1,
    "value": 10,
    "continuous": 4,
    "exists": 1,
    "arbitrarily": 2,
    "implies": 1,
    "continuity": 2,
    "point": 4,
    "python": 5,
    "def": 3,
    "exercises": 1,
    "check": 2,
    "import": 5,
    "practical": 1,
    "differentia": 1,
    "examples": 6,
    "true": 2,
    "finding": 4,
    "print": 7,
    "math": 2,
    "output": 4,
    "formulas": 4,
    "cos": 3,
    "return": 4,
    "code": 3,
    "example": 20,
    "then": 5,
    "given": 6,
    "cdot": 2,
    "respectively": 2,
    "changes": 1,
    "rule": 2,
    "respect": 2,
    "derivatives": 3,
    "rules": 2,
    "circ": 2,
    "derivative": 6,
    "where": 13,
    "composite": 2,
    "differentiation": 1,
    "chain": 2,
    "rate": 1,
    "integration": 4,
    "antiderivatives": 4,
    "another": 5,
    "whose": 3,
    "tangent": 1,
    "integral": 5,
    "called": 4,
    "antiderivative": 5,
    "ectively": 1,
    "graph": 1,
    "line": 1,
    "tiderivatives": 1,
    "indefinite": 1,
    "integrals": 2,
    "represents": 4,
    "constant": 3,
    "possible": 3,
    "int": 5,
    "16666666666667": 1,
    "area": 2,
    "curve": 3,
    "sphere": 1,
    "sympy": 2,
    "symbols": 2,
    "radius": 2,
    "integrate": 2,
    "vative": 1,
    "under": 2,
    "volume": 3,
    "applications": 1,
    "here": 2,
    "8169578969248": 1,
    "circle": 1,
    "form": 2,
    "vector": 6,
    "consists": 1,
    "binary": 1,
    "algebra": 1,
    "addition": 3,
    "produce": 1,
    "combines": 1,
    "set": 5,
    "used": 2,
    "satisfy": 1,
    "vectors": 5,
    "spanning": 2,
    "sets": 1,
    "two": 1,
    "space": 7,
    "collection": 2,
    "subtopics": 3,
    "structure": 1,
    "forms": 1,
    "elements": 1,
    "linear": 5,
    "definition": 10,
    "spaces": 1,
    "defined": 4,
    "operation": 1,
    "any": 3,
    "subspaces": 1,
    "conditions": 2,
    "subsets": 1,
    "operations": 2,
    "they": 1,
    "real": 3,
    "cannot": 1,
    "other": 1,
    "subtraction": 1,
    "expressed": 2,
    "include": 1,
    "independent": 5,
    "combination": 2,
    "over": 3,
    "mathbb": 3,
    "scalars": 3,
    "field": 1,
    "rational": 1,
    "independence": 3,
    "numbers": 3,
    "linearly": 4,
    "multiplication": 2,
    "arange": 1,
    "scalar": 1,
    "span": 1,
    "subspace": 1,
    "result": 2,
    "additive": 1,
    "identity": 1,
    "such": 1,
    "subseteq": 1,
    "entire": 1,
    "notations": 3,
    "define": 2,
    "plane": 1,
    "array": 3,
    "mathbf": 1,
    "solution": 2,
    "only": 2,
    "numpy": 2,
    "consider": 4,
    "equation": 3,
    "infinite": 2,
    "because": 1,
    "these": 1,
    "invertibility": 1,
    "non": 1,
    "matrix": 3,
    "representation": 1,
    "trivial": 1,
    "dimensional": 2,
    "represented": 4,
    "there": 1,
    "multiplying": 1,
    "gives": 1,
    "determinant": 2,
    "2x2": 1,
    "end": 1,
    "when": 1,
    "scaling": 1,
    "det": 2,
    "pmatrix": 1,
    "denoted": 1,
    "factor": 1,
    "begin": 1,
    "frac": 7,
    "adj": 1,
    "inverse": 1,
    "adjugate": 1,
    "transpose": 1,
    "cofactor": 1,
    "text": 1,
    "theorem": 3,
    "new": 2,
    "lands": 1,
    "likely": 1,
    "heads": 1,
    "our": 2,
    "beliefs": 2,
    "six": 7,
    "equal": 3,
    "rolling": 2,
    "occurring": 1,
    "face": 1,
    "basic": 1,
    "theory": 3,
    "chance": 1,
    "will": 5,
    "concepts": 1,
    "fair": 7,
    "event": 1,
    "has": 4,
    "landing": 1,
    "coin": 1,
    "already": 1,
    "measure": 2,
    "how": 2,
    "conditional": 1,
    "bayes": 2,
    "statistics": 1,
    "side": 1,
    "update": 2,
    "probability": 7,
    "occur": 1,
    "sided": 7,
    "die": 7,
    "each": 4,
    "getting": 1,
    "occurred": 1,
    "flip": 1,
    "allows": 2,
    "based": 2,
    "one": 3,
    "evidence": 2,
    "formula": 6,
    "use": 6,
    "sunny": 1,
    "measurable": 1,
    "experiment": 2,
    "between": 3,
    "what": 1,
    "number": 4,
    "sample": 2,
    "know": 1,
    "weather": 1,
    "variables": 2,
    "nition": 1,
    "find": 6,
    "variable": 5,
    "roll": 6,
    "tomorrow": 1,
    "rain": 1,
    "out": 2,
    "random": 5,
    "functions": 3,
    "deviation": 5,
    "shaped": 2,
    "distribution": 5,
    "their": 3,
    "corresponding": 1,
    "less": 1,
    "values": 3,
    "cumulative": 1,
    "cdf": 1,
    "takes": 1,
    "than": 1,
    "mean": 5,
    "bell": 2,
    "distributions": 3,
    "standard": 5,
    "have": 1,
    "probabilities": 1,
    "normal": 5,
    "outcomes": 1,
    "within": 1,
    "range": 1,
    "take": 1,
    "discrete": 1,
    "exponential": 2,
    "binomial": 1,
    "geometric": 1,
    "poisson": 1,
    "uniform": 2,
    "ormal": 1,
    "ribution": 1,
    "moments": 1,
    "average": 2,
    "long": 1,
    "repetitions": 1,
    "expected": 2,
    "run": 1,
    "variance": 3,
    "spread": 1,
    "distributed": 2,
    "approximately": 1,
    "var": 1,
    "sum": 1,
    "large": 1,
    "normally": 2,
    "states": 2,
    "central": 1,
    "identically": 1,
    "symmetric": 1,
    "times": 1,
    "males": 1,
    "about": 1,
    "united": 1,
    "many": 1,
    "approximate": 1,
    "heights": 1,
    "inches": 1,
    "buted": 1,
    "adult": 1,
    "exactly": 1,
    "expect": 1,
    "data": 1,
    "meaning": 1,
    "means": 1,
    "units": 1,
    "question": 1,
    "away": 1,
    "answer": 1,
    "chapters": 1,
    "focusing": 1,
    "certainly": 1,
    "section": 2,
    "advanced": 1,
    "covers": 2,
    "includes": 1,
    "substitution": 4,
    "improper": 1,
    "techniques": 1,
    "various": 2,
    "guide": 1,
    "comprehensive": 1,
    "original": 1,
    "becomes": 3,
    "simplifies": 1,
    "let": 3,
    "process": 1,
    "practice": 2,
    "review": 2,
    "recommended": 2,
    "sin": 2,
    "problems": 2,
    "ubstitution": 1,
    "exam": 2,
    "questions": 2,
    "equations": 2,
    "types": 1,
    "solutions": 2,
    "differential": 2,
    "more": 1,
    "ial": 1,
    "right": 1,
    "first": 2,
    "relates": 1,
    "left": 1,
    "quad": 1,
    "initial": 1,
    "problem": 1,
    "solve": 1
  },
  "doc_count": 29
}